README.md
setup.py
fren/__init__.py
fren/stone/__init__.py
fren/stone/core/__init__.py
fren/stone/core/util/StringUtils.py
fren/stone/core/util/__init__.py
fren_stone_core.egg-info/PKG-INFO
fren_stone_core.egg-info/SOURCES.txt
fren_stone_core.egg-info/dependency_links.txt
fren_stone_core.egg-info/top_level.txt