Metadata-Version: 2.1
Name: fren-stone-core
Version: 0.0.2
Summary: fren-stone-core
Home-page: UNKNOWN
Author: fren
Author-email: song_gis@163.com
License: MIT
Platform: UNKNOWN
Classifier: License :: OSI Approved :: MIT License
Classifier: Programming Language :: Python
Classifier: Programming Language :: Python :: 3
Classifier: Programming Language :: Python :: 3.6
Classifier: Programming Language :: Python :: Implementation :: CPython
Classifier: Programming Language :: Python :: Implementation :: PyPy
Requires-Python: >=3.6.0
